setup.py
WindyPie.egg-info/PKG-INFO
WindyPie.egg-info/SOURCES.txt
WindyPie.egg-info/dependency_links.txt
WindyPie.egg-info/requires.txt
WindyPie.egg-info/top_level.txt
socrata_python/Socrata.py
socrata_python/__init__.py
socrata_python/rss_capturer.py
socrata_python/setup.py
windypie/__init__.py
windypie/windypie.py