Metadata-Version: 1.0
Name: WindyPie
Version: 0.0.4
Summary: An easy-to-use wrapper for the Socrata API
Home-page: https://github.com/codeforamerica/windypie
Author: Jesse Bounds
Author-email: jesse@codeforamerica.org
License: BSD-style license; see the file LICENSE for details.
Platform: UNKNOWN
Classifier: Development Status :: 1 - Planning
Classifier: Intended Audience :: Developers
Classifier: Natural Language :: English
Classifier: License :: OSI Approved :: BSD License
Classifier: Programming Language :: Python
Classifier: Programming Language :: Python :: 2.6
Classifier: Programming Language :: Python :: 2.7
